adestis_netbox_domain_management/__init__.py
adestis_netbox_domain_management/navigation.py
adestis_netbox_domain_management/urls.py
adestis_netbox_domain_management/api/__init__.py
adestis_netbox_domain_management/api/urls.py
adestis_netbox_domain_management/api/views.py
adestis_netbox_domain_management/api/serializers/__init__.py
adestis_netbox_domain_management/api/serializers/domain_serializer.py
adestis_netbox_domain_management/filtersets/__init__.py
adestis_netbox_domain_management/filtersets/domain.py
adestis_netbox_domain_management/forms/__init__.py
adestis_netbox_domain_management/forms/domain.py
adestis_netbox_domain_management/migrations/0001_initial.py
adestis_netbox_domain_management/migrations/0002_alter_domain_options.py
adestis_netbox_domain_management/migrations/__init__.py
adestis_netbox_domain_management/models/__init__.py
adestis_netbox_domain_management/models/domain.py
adestis_netbox_domain_management/tables/__init__.py
adestis_netbox_domain_management/tables/domain.py
adestis_netbox_domain_management/templates/adestis_netbox_domain_management/domain.html
adestis_netbox_domain_management/templates/adestis_netbox_domain_management/domain_tenant.html
adestis_netbox_domain_management/views/__init__.py
adestis_netbox_domain_management/views/domain.py
adestis_netbox_domain_management-1.0.8.dist-info/LICENSE
adestis_netbox_domain_management-1.0.8.dist-info/METADATA
adestis_netbox_domain_management-1.0.8.dist-info/WHEEL
adestis_netbox_domain_management-1.0.8.dist-info/top_level.txt
adestis_netbox_domain_management-1.0.8.dist-info/RECORD
