Metadata-Version: 2.1
Name: adestis_netbox_domain_management
Version: 1.0.8
Summary: ADESTIS Domain Management
Home-page: https://github.com/an-adestis/ADESTIS-Netbox-Domain-Management/tree/master
Author: ADESTIS GmbH
Author-email: pypi@adestis.de
License: MIT License
Keywords: netbox,netbox-plugin,plugin
License-File: LICENSE
